{"ast":null,"code":"if (document.URL.match(/users/)) {\n  var chart = function chart() {\n    // タブメニュー表示\n    var StudyMenu = document.getElementById('StudyMenu');\n    var RelaxMenu = document.getElementById('RelaxMenu');\n    var FitnessMenu = document.getElementById('FitnessMenu');\n    var HobbyMenu = document.getElementById('HobbyMenu');\n    var Study_timers_chart = document.getElementById('Study_timers_chart');\n    var Relax_timers_chart = document.getElementById('Relax_timers_chart');\n    var Fitness_timers_chart = document.getElementById('Fitness_timers_chart');\n    var Hobby_timers_chart = document.getElementById('Hobby_timers_chart');\n    StudyMenu.addEventListener('click', function (e) {\n      e.preventDefault();\n      Relax_timers_chart.classList.add('hidden');\n      Fitness_timers_chart.classList.add('hidden');\n      Hobby_timers_chart.classList.add('hidden');\n      RelaxMenu.classList.remove('bg-green-400');\n      FitnessMenu.classList.remove('bg-red-400');\n      HobbyMenu.classList.remove('bg-purple-400');\n      RelaxMenu.classList.add('text-green-400');\n      FitnessMenu.classList.add('text-red-400');\n      HobbyMenu.classList.add('text-purple-400');\n      Study_timers_chart.classList.remove('hidden');\n      StudyMenu.classList.remove('text-blue-600');\n      StudyMenu.classList.add('bg-blue-600');\n      StudyMenu.classList.add('text-white');\n    });\n    RelaxMenu.addEventListener('click', function (e) {\n      e.preventDefault();\n      Study_timers_chart.classList.add('hidden');\n      Fitness_timers_chart.classList.add('hidden');\n      Hobby_timers_chart.classList.add('hidden');\n      StudyMenu.classList.remove('bg-blue-600');\n      FitnessMenu.classList.remove('bg-red-400');\n      HobbyMenu.classList.remove('bg-purple-400');\n      StudyMenu.classList.add('text-blue-600');\n      FitnessMenu.classList.add('text-red-400');\n      HobbyMenu.classList.add('text-purple-400');\n      Relax_timers_chart.classList.remove('hidden');\n      RelaxMenu.classList.remove('text-green-400');\n      RelaxMenu.classList.add('bg-green-400');\n      RelaxMenu.classList.add('text-white');\n    });\n    FitnessMenu.addEventListener('click', function (e) {\n      e.preventDefault();\n      Study_timers_chart.classList.add('hidden');\n      Relax_timers_chart.classList.add('hidden');\n      Hobby_timers_chart.classList.add('hidden');\n      StudyMenu.classList.remove('bg-blue-600');\n      RelaxMenu.classList.remove('bg-green-400');\n      HobbyMenu.classList.remove('bg-purple-400');\n      StudyMenu.classList.add('text-blue-600');\n      RelaxMenu.classList.add('text-green-400');\n      HobbyMenu.classList.add('text-purple-400');\n      Fitness_timers_chart.classList.remove('hidden');\n      FitnessMenu.classList.remove('text-red-400');\n      FitnessMenu.classList.add('bg-red-400');\n      FitnessMenu.classList.add('text-white');\n    });\n    HobbyMenu.addEventListener('click', function (e) {\n      e.preventDefault();\n      Study_timers_chart.classList.add('hidden');\n      Relax_timers_chart.classList.add('hidden');\n      Fitness_timers_chart.classList.add('hidden');\n      StudyMenu.classList.remove('bg-blue-600');\n      RelaxMenu.classList.remove('bg-green-400');\n      FitnessMenu.classList.remove('bg-red-400');\n      StudyMenu.classList.add('text-blue-600');\n      RelaxMenu.classList.add('text-green-400');\n      FitnessMenu.classList.add('text-red-400');\n      Hobby_timers_chart.classList.remove('hidden');\n      HobbyMenu.classList.remove('text-purple-400');\n      HobbyMenu.classList.add('bg-purple-400');\n      HobbyMenu.classList.add('text-white');\n    });\n  };\n\n  window.addEventListener('load', chart);\n}","map":{"version":3,"sources":["/Timmick/app/javascript/Users/show.js"],"names":["document","URL","match","chart","StudyMenu","getElementById","RelaxMenu","FitnessMenu","HobbyMenu","Study_timers_chart","Relax_timers_chart","Fitness_timers_chart","Hobby_timers_chart","addEventListener","e","preventDefault","classList","add","remove","window"],"mappings":"AAAA,IAAIA,QAAQ,CAACC,GAAT,CAAaC,KAAb,CAAoB,OAApB,CAAJ,EAAmC;AAAA,MAExBC,KAFwB,GAEjC,SAASA,KAAT,GAAiB;AACf;AACA,QAAMC,SAAS,GAAGJ,QAAQ,CAACK,cAAT,CAAwB,WAAxB,CAAlB;AACA,QAAMC,SAAS,GAAGN,QAAQ,CAACK,cAAT,CAAwB,WAAxB,CAAlB;AACA,QAAME,WAAW,GAAGP,QAAQ,CAACK,cAAT,CAAwB,aAAxB,CAApB;AACA,QAAMG,SAAS,GAAGR,QAAQ,CAACK,cAAT,CAAwB,WAAxB,CAAlB;AACA,QAAMI,kBAAkB,GAAGT,QAAQ,CAACK,cAAT,CAAwB,oBAAxB,CAA3B;AACA,QAAMK,kBAAkB,GAAGV,QAAQ,CAACK,cAAT,CAAwB,oBAAxB,CAA3B;AACA,QAAMM,oBAAoB,GAAGX,QAAQ,CAACK,cAAT,CAAwB,sBAAxB,CAA7B;AACA,QAAMO,kBAAkB,GAAGZ,QAAQ,CAACK,cAAT,CAAwB,oBAAxB,CAA3B;AAEAD,IAAAA,SAAS,CAACS,gBAAV,CAA2B,OAA3B,EAAoC,UAACC,CAAD,EAAO;AACzCA,MAAAA,CAAC,CAACC,cAAF;AAEAL,MAAAA,kBAAkB,CAACM,SAAnB,CAA6BC,GAA7B,CAAiC,QAAjC;AACAN,MAAAA,oBAAoB,CAACK,SAArB,CAA+BC,GAA/B,CAAmC,QAAnC;AACAL,MAAAA,kBAAkB,CAACI,SAAnB,CAA6BC,GAA7B,CAAiC,QAAjC;AAEAX,MAAAA,SAAS,CAACU,SAAV,CAAoBE,MAApB,CAA2B,cAA3B;AACAX,MAAAA,WAAW,CAACS,SAAZ,CAAsBE,MAAtB,CAA6B,YAA7B;AACAV,MAAAA,SAAS,CAACQ,SAAV,CAAoBE,MAApB,CAA2B,eAA3B;AAEAZ,MAAAA,SAAS,CAACU,SAAV,CAAoBC,GAApB,CAAwB,gBAAxB;AACAV,MAAAA,WAAW,CAACS,SAAZ,CAAsBC,GAAtB,CAA0B,cAA1B;AACAT,MAAAA,SAAS,CAACQ,SAAV,CAAoBC,GAApB,CAAwB,iBAAxB;AAEAR,MAAAA,kBAAkB,CAACO,SAAnB,CAA6BE,MAA7B,CAAoC,QAApC;AACAd,MAAAA,SAAS,CAACY,SAAV,CAAoBE,MAApB,CAA2B,eAA3B;AACAd,MAAAA,SAAS,CAACY,SAAV,CAAoBC,GAApB,CAAwB,aAAxB;AACAb,MAAAA,SAAS,CAACY,SAAV,CAAoBC,GAApB,CAAwB,YAAxB;AACD,KAnBD;AAqBAX,IAAAA,SAAS,CAACO,gBAAV,CAA2B,OAA3B,EAAoC,UAACC,CAAD,EAAO;AACzCA,MAAAA,CAAC,CAACC,cAAF;AAEAN,MAAAA,kBAAkB,CAACO,SAAnB,CAA6BC,GAA7B,CAAiC,QAAjC;AACAN,MAAAA,oBAAoB,CAACK,SAArB,CAA+BC,GAA/B,CAAmC,QAAnC;AACAL,MAAAA,kBAAkB,CAACI,SAAnB,CAA6BC,GAA7B,CAAiC,QAAjC;AAEAb,MAAAA,SAAS,CAACY,SAAV,CAAoBE,MAApB,CAA2B,aAA3B;AACAX,MAAAA,WAAW,CAACS,SAAZ,CAAsBE,MAAtB,CAA6B,YAA7B;AACAV,MAAAA,SAAS,CAACQ,SAAV,CAAoBE,MAApB,CAA2B,eAA3B;AAEAd,MAAAA,SAAS,CAACY,SAAV,CAAoBC,GAApB,CAAwB,eAAxB;AACAV,MAAAA,WAAW,CAACS,SAAZ,CAAsBC,GAAtB,CAA0B,cAA1B;AACAT,MAAAA,SAAS,CAACQ,SAAV,CAAoBC,GAApB,CAAwB,iBAAxB;AAEAP,MAAAA,kBAAkB,CAACM,SAAnB,CAA6BE,MAA7B,CAAoC,QAApC;AACAZ,MAAAA,SAAS,CAACU,SAAV,CAAoBE,MAApB,CAA2B,gBAA3B;AACAZ,MAAAA,SAAS,CAACU,SAAV,CAAoBC,GAApB,CAAwB,cAAxB;AACAX,MAAAA,SAAS,CAACU,SAAV,CAAoBC,GAApB,CAAwB,YAAxB;AACD,KAnBD;AAqBAV,IAAAA,WAAW,CAACM,gBAAZ,CAA6B,OAA7B,EAAsC,UAACC,CAAD,EAAO;AAC3CA,MAAAA,CAAC,CAACC,cAAF;AAEAN,MAAAA,kBAAkB,CAACO,SAAnB,CAA6BC,GAA7B,CAAiC,QAAjC;AACAP,MAAAA,kBAAkB,CAACM,SAAnB,CAA6BC,GAA7B,CAAiC,QAAjC;AACAL,MAAAA,kBAAkB,CAACI,SAAnB,CAA6BC,GAA7B,CAAiC,QAAjC;AAEAb,MAAAA,SAAS,CAACY,SAAV,CAAoBE,MAApB,CAA2B,aAA3B;AACAZ,MAAAA,SAAS,CAACU,SAAV,CAAoBE,MAApB,CAA2B,cAA3B;AACAV,MAAAA,SAAS,CAACQ,SAAV,CAAoBE,MAApB,CAA2B,eAA3B;AAEAd,MAAAA,SAAS,CAACY,SAAV,CAAoBC,GAApB,CAAwB,eAAxB;AACAX,MAAAA,SAAS,CAACU,SAAV,CAAoBC,GAApB,CAAwB,gBAAxB;AACAT,MAAAA,SAAS,CAACQ,SAAV,CAAoBC,GAApB,CAAwB,iBAAxB;AAEAN,MAAAA,oBAAoB,CAACK,SAArB,CAA+BE,MAA/B,CAAsC,QAAtC;AACAX,MAAAA,WAAW,CAACS,SAAZ,CAAsBE,MAAtB,CAA6B,cAA7B;AACAX,MAAAA,WAAW,CAACS,SAAZ,CAAsBC,GAAtB,CAA0B,YAA1B;AACAV,MAAAA,WAAW,CAACS,SAAZ,CAAsBC,GAAtB,CAA0B,YAA1B;AACD,KAnBD;AAqBAT,IAAAA,SAAS,CAACK,gBAAV,CAA2B,OAA3B,EAAoC,UAACC,CAAD,EAAO;AACzCA,MAAAA,CAAC,CAACC,cAAF;AAEAN,MAAAA,kBAAkB,CAACO,SAAnB,CAA6BC,GAA7B,CAAiC,QAAjC;AACAP,MAAAA,kBAAkB,CAACM,SAAnB,CAA6BC,GAA7B,CAAiC,QAAjC;AACAN,MAAAA,oBAAoB,CAACK,SAArB,CAA+BC,GAA/B,CAAmC,QAAnC;AAEAb,MAAAA,SAAS,CAACY,SAAV,CAAoBE,MAApB,CAA2B,aAA3B;AACAZ,MAAAA,SAAS,CAACU,SAAV,CAAoBE,MAApB,CAA2B,cAA3B;AACAX,MAAAA,WAAW,CAACS,SAAZ,CAAsBE,MAAtB,CAA6B,YAA7B;AAEAd,MAAAA,SAAS,CAACY,SAAV,CAAoBC,GAApB,CAAwB,eAAxB;AACAX,MAAAA,SAAS,CAACU,SAAV,CAAoBC,GAApB,CAAwB,gBAAxB;AACAV,MAAAA,WAAW,CAACS,SAAZ,CAAsBC,GAAtB,CAA0B,cAA1B;AAEAL,MAAAA,kBAAkB,CAACI,SAAnB,CAA6BE,MAA7B,CAAoC,QAApC;AACAV,MAAAA,SAAS,CAACQ,SAAV,CAAoBE,MAApB,CAA2B,iBAA3B;AACAV,MAAAA,SAAS,CAACQ,SAAV,CAAoBC,GAApB,CAAwB,eAAxB;AACAT,MAAAA,SAAS,CAACQ,SAAV,CAAoBC,GAApB,CAAwB,YAAxB;AACD,KAnBD;AAoBD,GAhGgC;;AAkGjCE,EAAAA,MAAM,CAACN,gBAAP,CAAwB,MAAxB,EAAgCV,KAAhC;AACD","sourcesContent":["if (document.URL.match( /users/ )) {\n  \n  function chart() {\n    // タブメニュー表示\n    const StudyMenu = document.getElementById('StudyMenu');\n    const RelaxMenu = document.getElementById('RelaxMenu');\n    const FitnessMenu = document.getElementById('FitnessMenu');\n    const HobbyMenu = document.getElementById('HobbyMenu');\n    const Study_timers_chart = document.getElementById('Study_timers_chart');\n    const Relax_timers_chart = document.getElementById('Relax_timers_chart');\n    const Fitness_timers_chart = document.getElementById('Fitness_timers_chart');\n    const Hobby_timers_chart = document.getElementById('Hobby_timers_chart');\n    \n    StudyMenu.addEventListener('click', (e) => {\n      e.preventDefault();\n      \n      Relax_timers_chart.classList.add('hidden');\n      Fitness_timers_chart.classList.add('hidden');\n      Hobby_timers_chart.classList.add('hidden');\n      \n      RelaxMenu.classList.remove('bg-green-400');\n      FitnessMenu.classList.remove('bg-red-400');\n      HobbyMenu.classList.remove('bg-purple-400');\n      \n      RelaxMenu.classList.add('text-green-400');\n      FitnessMenu.classList.add('text-red-400');\n      HobbyMenu.classList.add('text-purple-400');\n      \n      Study_timers_chart.classList.remove('hidden');\n      StudyMenu.classList.remove('text-blue-600');\n      StudyMenu.classList.add('bg-blue-600');\n      StudyMenu.classList.add('text-white');\n    });\n\n    RelaxMenu.addEventListener('click', (e) => {\n      e.preventDefault();\n      \n      Study_timers_chart.classList.add('hidden');\n      Fitness_timers_chart.classList.add('hidden');\n      Hobby_timers_chart.classList.add('hidden');\n      \n      StudyMenu.classList.remove('bg-blue-600');\n      FitnessMenu.classList.remove('bg-red-400');\n      HobbyMenu.classList.remove('bg-purple-400');\n      \n      StudyMenu.classList.add('text-blue-600');\n      FitnessMenu.classList.add('text-red-400');\n      HobbyMenu.classList.add('text-purple-400');\n      \n      Relax_timers_chart.classList.remove('hidden');\n      RelaxMenu.classList.remove('text-green-400');\n      RelaxMenu.classList.add('bg-green-400');\n      RelaxMenu.classList.add('text-white');\n    });\n\n    FitnessMenu.addEventListener('click', (e) => {\n      e.preventDefault();\n      \n      Study_timers_chart.classList.add('hidden');\n      Relax_timers_chart.classList.add('hidden');\n      Hobby_timers_chart.classList.add('hidden');\n      \n      StudyMenu.classList.remove('bg-blue-600');\n      RelaxMenu.classList.remove('bg-green-400');\n      HobbyMenu.classList.remove('bg-purple-400');\n      \n      StudyMenu.classList.add('text-blue-600');\n      RelaxMenu.classList.add('text-green-400');\n      HobbyMenu.classList.add('text-purple-400');\n      \n      Fitness_timers_chart.classList.remove('hidden');\n      FitnessMenu.classList.remove('text-red-400');\n      FitnessMenu.classList.add('bg-red-400');\n      FitnessMenu.classList.add('text-white');\n    });\n    \n    HobbyMenu.addEventListener('click', (e) => {\n      e.preventDefault();\n      \n      Study_timers_chart.classList.add('hidden');\n      Relax_timers_chart.classList.add('hidden');\n      Fitness_timers_chart.classList.add('hidden');\n      \n      StudyMenu.classList.remove('bg-blue-600');\n      RelaxMenu.classList.remove('bg-green-400');\n      FitnessMenu.classList.remove('bg-red-400');\n      \n      StudyMenu.classList.add('text-blue-600');\n      RelaxMenu.classList.add('text-green-400');\n      FitnessMenu.classList.add('text-red-400');\n      \n      Hobby_timers_chart.classList.remove('hidden');\n      HobbyMenu.classList.remove('text-purple-400');\n      HobbyMenu.classList.add('bg-purple-400');\n      HobbyMenu.classList.add('text-white');\n    });\n  }\n\n  window.addEventListener('load', chart)\n}"]},"metadata":{},"sourceType":"module"}